setup.py
kagisho/Binomialdistribution.py
kagisho/Gaussiandistribution.py
kagisho/Generaldistribution.py
kagisho/__init__.py
kagisho.egg-info/PKG-INFO
kagisho.egg-info/SOURCES.txt
kagisho.egg-info/dependency_links.txt
kagisho.egg-info/not-zip-safe
kagisho.egg-info/top_level.txt