Metadata-Version: 1.0
Name: kagisho
Version: 0.1
Summary: Gaussian distributions
Home-page: UNKNOWN
Author: nkadimeng
Author-email: UNKNOWN
License: UNKNOWN
Platform: UNKNOWN
